ba_syx_submodel_repository_client/__init__.py
ba_syx_submodel_repository_client/api/__init__.py
ba_syx_submodel_repository_client/api/asset_administration_shell_api/__init__.py
ba_syx_submodel_repository_client/api/asset_administration_shell_api/delete_file_by_path.py
ba_syx_submodel_repository_client/api/asset_administration_shell_api/get_file_by_path.py
ba_syx_submodel_repository_client/api/asset_administration_shell_api/put_file_by_path.py
ba_syx_submodel_repository_client/api/registry_and_discovery_interface/__init__.py
ba_syx_submodel_repository_client/api/registry_and_discovery_interface/get_description.py
ba_syx_submodel_repository_client/api/submodel_repository_api/__init__.py
ba_syx_submodel_repository_client/api/submodel_repository_api/delete_submodel_by_id.py
ba_syx_submodel_repository_client/api/submodel_repository_api/delete_submodel_element_by_path_submodel_repo.py
ba_syx_submodel_repository_client/api/submodel_repository_api/get_all_submodel_elements.py
ba_syx_submodel_repository_client/api/submodel_repository_api/get_all_submodels.py
ba_syx_submodel_repository_client/api/submodel_repository_api/get_submodel_by_id.py
ba_syx_submodel_repository_client/api/submodel_repository_api/get_submodel_by_id_metadata.py
ba_syx_submodel_repository_client/api/submodel_repository_api/get_submodel_by_id_value_only.py
ba_syx_submodel_repository_client/api/submodel_repository_api/get_submodel_element_by_path_submodel_repo.py
ba_syx_submodel_repository_client/api/submodel_repository_api/get_submodel_element_by_path_value_only_submodel_repo.py
ba_syx_submodel_repository_client/api/submodel_repository_api/invoke_operation_submodel_repo.py
ba_syx_submodel_repository_client/api/submodel_repository_api/patch_submodel_element_by_path_value_only_submodel_repo.py
ba_syx_submodel_repository_client/api/submodel_repository_api/post_submodel.py
ba_syx_submodel_repository_client/api/submodel_repository_api/post_submodel_element_by_path_submodel_repo.py
ba_syx_submodel_repository_client-3.0.dist-info/METADATA
ba_syx_submodel_repository_client-3.0.dist-info/WHEEL
ba_syx_submodel_repository_client-3.0.dist-info/RECORD
